remove_print_statements.py
remove_print_statements-0.5.2.dist-info/LICENSE
remove_print_statements-0.5.2.dist-info/METADATA
remove_print_statements-0.5.2.dist-info/WHEEL
remove_print_statements-0.5.2.dist-info/entry_points.txt
remove_print_statements-0.5.2.dist-info/RECORD
