Metadata-Version: 2.1
Name: remove-print-statements
Version: 0.5.2
Summary: A command-line tool (and pre-commit hook) to remove print statements from your Python project.
Home-page: https://github.com/dhruvmanila/remove-print-statements
License: MIT
Keywords: python,codemod,libCST
Author: Dhruv Manilawala
Author-email: dhruvmanila@gmail.com
Requires-Python: >=3.7,<4.0
Classifier: Development Status :: 4 - Beta
Classifier: Environment :: Console
Classifier: Intended Audience :: Developers
Classifier: License :: OSI Approved :: MIT License
Classifier: Operating System :: MacOS
Classifier: Operating System :: Microsoft :: Windows
Classifier: Operating System :: POSIX :: Linux
Classifier: Programming Language :: Python :: 3
Classifier: Programming Language :: Python :: 3.7
Classifier: Programming Language :: Python :: 3.8
Classifier: Programming Language :: Python :: 3.9
Classifier: Programming Language :: Python :: 3.10
Classifier: Programming Language :: Python :: 3.11
Classifier: Typing :: Typed
Requires-Dist: click (>=8.1.1)
Requires-Dist: libcst (>=0.4.2,<0.5.0)
Project-URL: Bug Tracker, https://github.com/dhruvmanila/remove-print-statements/issues
Project-URL: Repository, https://github.com/dhruvmanila/remove-print-statements
